adoreta/__init__.py
adoreta/log.py
adoreta-0.0.4.dist-info/LICENSE.txt
adoreta-0.0.4.dist-info/METADATA
adoreta-0.0.4.dist-info/WHEEL
adoreta-0.0.4.dist-info/top_level.txt
adoreta-0.0.4.dist-info/RECORD
