Metadata-Version: 2.1
Name: adoreta
Version: 0.0.4
Summary: Simple Logging using CSV
Home-page: https://github.com/ansari-akram/adoreta
Author: Ansari Akram
Author-email: ansariakramobaid@gmail.com
License: GNU GPLv3
Keywords: log
Platform: UNKNOWN
License-File: LICENSE.txt
Requires-Dist: prettytable
